{
  "name": "Cop",
  "type": "role",
  "folder": null,
  "system": {
    "flavor": "Beat, traffic, vice, robbery, homicide, SWAT, Max-Tac, riot, or internal affairs.",
    "notes": "",
    "cost": 0,
    "weight": 0,
    "availability": "common",
    "equipped": false,
    "source": "Core Rulebook, p.11",
    "specialAbility": {
      "name": "Authority",
      "description": "The ability to intimidate and control others through your position as a lawman."
    },
    "specialSkill": {
      "uuid": "Compendium.cyberpunk.skills.Item.v19DthwbNB58wPDK",
      "name": "Authority"
    },
    "careerSkills": [
      {
        "name": "Awareness/Notice",
        "uuid": "Compendium.cyberpunk.skills.Item.OnPqPYxHVsucA6hJ"
      },
      {
        "name": "Handgun",
        "uuid": "Compendium.cyberpunk.skills.Item.certlnd58KDZWWr1"
      },
      {
        "name": "Human Perception",
        "uuid": "Compendium.cyberpunk.skills.Item.m45zKvPpjD13V0kf"
      },
      {
        "name": "Athletics",
        "uuid": "Compendium.cyberpunk.skills.Item.zIS6P8CbO9nkMiS3"
      },
      {
        "name": "Education & General Knowledge",
        "uuid": "Compendium.cyberpunk.skills.Item.zWypBZBLKTJW6NOA"
      },
      {
        "name": "Brawling",
        "uuid": "Compendium.cyberpunk.skills.Item.Dye8VHlLnX2LJpDk"
      },
      {
        "name": "Melee",
        "uuid": "Compendium.cyberpunk.skills.Item.ECffcV0OmyLfwcuL"
      },
      {
        "name": "Interrogation",
        "uuid": "Compendium.cyberpunk.skills.Item.ru0kzxjKSshcf3Zp"
      },
      {
        "name": "Streetwise",
        "uuid": "Compendium.cyberpunk.skills.Item.lR8vyv0AbqZcOBlA"
      }
    ]
  },
  "_id": "eURdZs63WG081qf0",
  "img": "systems/cyberpunk/img/svg/placeholder-role.svg",
  "effects": [],
  "flags": {},
  "_stats": {
    "compendiumSource": null,
    "duplicateSource": null,
    "exportSource": null,
    "coreVersion": "13.350",
    "systemId": "cyberpunk",
    "systemVersion": "1.0.5",
    "createdTime": 1772494978905,
    "modifiedTime": 1773332932257,
    "lastModifiedBy": null
  },
  "ownership": {
    "default": 0
  },
  "sort": 0,
  "_key": "!items!eURdZs63WG081qf0"
}
