{
  "name": "Divemaster",
  "type": "role",
  "folder": null,
  "system": {
    "flavor": "Underwater mining specialist combining diving expertise with heavy equipment operation.",
    "notes": "",
    "cost": 0,
    "weight": 0,
    "availability": "common",
    "equipped": false,
    "source": "Stormfront, p.24",
    "specialAbility": {
      "name": "Aquatic Sense",
      "description": "Adds full level to Awareness/Notice, and half level to Initiative while underwater."
    },
    "specialSkill": {
      "uuid": "Compendium.cyberpunk.skills.Item.kkJE8fVoa2bjm6yY",
      "name": "Aquatic Sense"
    },
    "careerSkills": [
      {
        "uuid": "Compendium.cyberpunk.skills.Item.OnPqPYxHVsucA6hJ",
        "name": "Awareness/Notice"
      },
      {
        "uuid": "Compendium.cyberpunk.skills.Item.8EsYuEZYIWAsMHXt",
        "name": "Endurance"
      },
      {
        "uuid": "Compendium.cyberpunk.skills.Item.FOBex5G84csZdtH2",
        "name": "Pilot: EVPA"
      },
      {
        "uuid": "Compendium.cyberpunk.skills.Item.czMmwpK3y5oC7IlV",
        "name": "Pilot: Hardshell"
      },
      {
        "uuid": "Compendium.cyberpunk.skills.Item.5SW2N62k0pm03KX9",
        "name": "Pressure Suit Tech"
      },
      {
        "uuid": "Compendium.cyberpunk.skills.Item.kbfc6xFH8UC7dIRb",
        "name": "Operate Heavy Machinery"
      },
      {
        "uuid": "Compendium.cyberpunk.skills.Item.Q8HVRpd4LCmFsST0",
        "name": "Underwater Combat"
      },
      {
        "uuid": "Compendium.cyberpunk.skills.Item.yJndiuBMgUDv2Tbd",
        "name": "Underwater Survival"
      },
      {
        "uuid": "Compendium.cyberpunk.skills.Item.npdNJeTeRHnkPVfV",
        "name": "Underwater Weapons"
      }
    ]
  },
  "_id": "FTFdpnhDj34TtCNm",
  "img": "systems/cyberpunk/img/svg/placeholder-role.svg",
  "effects": [],
  "flags": {},
  "_stats": {
    "compendiumSource": null,
    "duplicateSource": null,
    "exportSource": null,
    "coreVersion": "13.350",
    "systemId": "cyberpunk",
    "systemVersion": "1.0.4",
    "createdTime": 1772494978905,
    "modifiedTime": 1780331638522,
    "lastModifiedBy": null
  },
  "ownership": {
    "default": 0
  },
  "sort": 0,
  "_key": "!items!FTFdpnhDj34TtCNm"
}
